sklearn/__init__.py
sklearn/_config.py
sklearn/_distributor_init.py
sklearn/_isotonic.c
sklearn/_isotonic.cpython-312.so
sklearn/_isotonic.py
sklearn/_isotonic.pyx
sklearn/_min_dependencies.py
sklearn/base.py
sklearn/calibration.py
sklearn/conftest.py
sklearn/discriminant_analysis.py
sklearn/dummy.py
sklearn/exceptions.py
sklearn/isotonic.py
sklearn/kernel_approximation.py
sklearn/kernel_ridge.py
sklearn/meson.build
sklearn/multiclass.py
sklearn/multioutput.py
sklearn/naive_bayes.py
sklearn/pipeline.py
sklearn/random_projection.py
sklearn/__check_build/__init__.py
sklearn/__check_build/_check_build.c
sklearn/__check_build/_check_build.cpython-312.so
sklearn/__check_build/_check_build.py
sklearn/__check_build/_check_build.pyx
sklearn/__check_build/meson.build
sklearn/_build_utils/__init__.py
sklearn/_build_utils/openmp_helpers.py
sklearn/_build_utils/pre_build_helpers.py
sklearn/_build_utils/tempita.py
sklearn/_build_utils/version.py
sklearn/_loss/__init__.py
sklearn/_loss/_loss.c
sklearn/_loss/_loss.cpython-312.so
sklearn/_loss/_loss.pxd
sklearn/_loss/_loss.py
sklearn/_loss/_loss.pyx
sklearn/_loss/_loss.pyx.tp
sklearn/_loss/link.py
sklearn/_loss/loss.py
sklearn/_loss/meson.build
sklearn/_loss/tests/__init__.py
sklearn/_loss/tests/test_link.py
sklearn/_loss/tests/test_loss.py
sklearn/cluster/__init__.py
sklearn/cluster/_affinity_propagation.py
sklearn/cluster/_agglomerative.py
sklearn/cluster/_bicluster.py
sklearn/cluster/_birch.py
sklearn/cluster/_bisect_k_means.py
sklearn/cluster/_dbscan.py
sklearn/cluster/_dbscan_inner.cpp
sklearn/cluster/_dbscan_inner.cpython-312.so
sklearn/cluster/_dbscan_inner.py
sklearn/cluster/_dbscan_inner.pyx
sklearn/cluster/_feature_agglomeration.py
sklearn/cluster/_hierarchical_fast.cpp
sklearn/cluster/_hierarchical_fast.cpython-312.so
sklearn/cluster/_hierarchical_fast.pxd
sklearn/cluster/_hierarchical_fast.py
sklearn/cluster/_hierarchical_fast.pyx
sklearn/cluster/_k_means_common.c
sklearn/cluster/_k_means_common.cpython-312.so
scikit_learn_aipy-1.5.2.dist-info/METADATA
scikit_learn_aipy-1.5.2.dist-info/WHEEL
scikit_learn_aipy-1.5.2.dist-info/top_level.txt
scikit_learn_aipy-1.5.2.dist-info/RECORD
