Metadata-Version: 2.4
Name: scikit-learn-aipy
Version: 1.5.2
Summary: A set of python modules for machine learning and data mining
Author-email: The QPYPI Team <qpypi@qpython.org>
License: BSD
Project-URL: Homepage, https://qpypi.qpython.org/project/scikit-learn-aipy/
Classifier: Intended Audience :: Developers
Classifier: Intended Audience :: Education
Classifier: Intended Audience :: Information Technology
Classifier: Intended Audience :: End Users/Desktop
Classifier: License :: OSI Approved :: Apache Software License
Classifier: Operating System :: Android
Classifier: Programming Language :: Python
Classifier: Programming Language :: Python :: 3.12
Classifier: Topic :: Software Development
Requires-Python: ==3.12.*
Requires-Dist: scipy-aipy
Requires-Dist: numpy-aipy
Requires-Dist: joblib
Requires-Dist: threadpoolctl
